Topsis_Lakshita_102303505/__init__.py
Topsis_Lakshita_102303505/__main__.py
Topsis_Lakshita_102303505/topsis.py
topsis_lakshita_102303505-1.0.0.dist-info/licenses/LICENSE
topsis_lakshita_102303505-1.0.0.dist-info/METADATA
topsis_lakshita_102303505-1.0.0.dist-info/WHEEL
topsis_lakshita_102303505-1.0.0.dist-info/entry_points.txt
topsis_lakshita_102303505-1.0.0.dist-info/top_level.txt
topsis_lakshita_102303505-1.0.0.dist-info/RECORD
