Metadata-Version: 2.4
Name: Topsis-Lakshita-102303505
Version: 1.0.0
Summary: A Python package for TOPSIS multi-criteria decision analysis
Home-page: https://github.com/Lakshita018/topsis
Author: Lakshita Gupta
Author-email: lakshitagupta0518@gmail.com
Project-URL: Bug Reports, https://github.com/Lakshita018/topsis/issues
Project-URL: Source, https://github.com/Lakshita018/topsis
Keywords: topsis,multi-criteria decision analysis,mcdm,decision making
Classifier: Development Status :: 5 - Production/Stable
Classifier: Intended Audience :: Developers
Classifier: Intended Audience :: Science/Research
Classifier: Topic :: Scientific/Engineering :: Mathematics
Classifier: License :: OSI Approved :: MIT License
Classifier: Programming Language :: Python :: 3
Classifier: Programming Language :: Python :: 3.7
Classifier: Programming Language :: Python :: 3.8
Classifier: Programming Language :: Python :: 3.9
Classifier: Programming Language :: Python :: 3.10
Classifier: Programming Language :: Python :: 3.11
Classifier: Operating System :: OS Independent
Requires-Python: >=3.7
License-File: LICENSE
Requires-Dist: pandas>=1.0.0
Requires-Dist: numpy>=1.18.0
Requires-Dist: openpyxl>=3.0.0
Dynamic: author
Dynamic: author-email
Dynamic: classifier
Dynamic: description
Dynamic: description-content-type
Dynamic: home-page
Dynamic: keywords
Dynamic: license-file
Dynamic: project-url
Dynamic: requires-dist
Dynamic: requires-python
Dynamic: summary
